rtorrent_rpc/__init__.py
rtorrent_rpc/_jsonrpc.py
rtorrent_rpc/_scgi.py
rtorrent_rpc/_transport.py
rtorrent_rpc/helper.py
rtorrent_rpc/py.typed
rtorrent_rpc-0.9.4.dist-info/LICENSE
rtorrent_rpc-0.9.4.dist-info/WHEEL
rtorrent_rpc-0.9.4.dist-info/METADATA
rtorrent_rpc-0.9.4.dist-info/RECORD
