Metadata-Version: 2.1
Name: rtorrent-rpc
Version: 0.9.4
Summary: Typed rtorrent rpc client
Keywords: rtorrent,rpc
Author-email: trim21 <trim21me@gmail.com>
Requires-Python: ~=3.8
Classifier: Intended Audience :: Developers
Classifier: Development Status :: 4 - Beta
Classifier: License :: OSI Approved :: MIT License
Classifier: Programming Language :: Python :: 3 :: Only
Requires-Dist: urllib3~=2.2
Requires-Dist: bencode2>=0.3.0,<1
Requires-Dist: certifi>=2017.4.17
Requires-Dist: typing-extensions>=4.7.1
Requires-Dist: pytest==8.3.2 ; extra == "dev"
Requires-Dist: pytest-github-actions-annotate-failures==0.2.0 ; extra == "dev"
Requires-Dist: coverage==7.6.1 ; extra == "dev"
Requires-Dist: pre-commit==3.8.0 ; extra == "dev" and ( python_version >= "3.9")
Requires-Dist: sphinx-autobuild==2024.10.2 ; extra == "dev" and ( python_version >= "3.9")
Requires-Dist: mypy==1.11.2 ; extra == "dev" and ( python_version >= "3.9")
Requires-Dist: sphinx~=8.0 ; extra == "docs" and ( python_version >= "3.9")
Requires-Dist: furo~=2024.0 ; extra == "docs" and ( python_version >= "3.9")
Requires-Dist: orjson~=3.0 ; extra == "orjson"
Project-URL: Homepage, https://github.com/trim21/rtorrent-rpc
Provides-Extra: dev
Provides-Extra: docs
Provides-Extra: orjson
